imlmlib/ACTR_2005.py
imlmlib/__init__.py
imlmlib/exponential_forgetting.py
imlmlib/mem_utils.py
imlmlib/mle_utils.py
imlmlib-0.0.1.dist-info/LICENSE
imlmlib-0.0.1.dist-info/WHEEL
imlmlib-0.0.1.dist-info/METADATA
imlmlib-0.0.1.dist-info/RECORD
