Metadata-Version: 2.1
Name: imlmlib
Version: 0.0.1
Summary: Utilities for parametric modeling of interaction modalities that leverage memory
License: MIT
Author: jgori
Author-email: juliengori@gmail.com
Requires-Python: >=3.8,<3.12
Classifier: License :: OSI Approved :: MIT License
Classifier: Programming Language :: Python :: 3
Classifier: Programming Language :: Python :: 3.10
Classifier: Programming Language :: Python :: 3.8
Classifier: Programming Language :: Python :: 3.9
Requires-Dist: numpy (>=1.24.2,<2.0.0)
Requires-Dist: scipy (>=1.10.1,<2.0.0)
